esp_debug_backend/__init__.py
esp_debug_backend/defs.py
esp_debug_backend/gdb.py
esp_debug_backend/gdb_helpers.py
esp_debug_backend/log.py
esp_debug_backend/oocd.py
esp_debug_backend/utils.py
esp_debug_backend/hw_specific/__init__.py
esp_debug_backend/hw_specific/esp.py
esp_debug_backend/hw_specific/esp_init.gdb
esp_debug_backend/hw_specific/riscv.py
esp_debug_backend/hw_specific/xtensa.py
esp_debug_backend-1.0.3.dist-info/LICENSE
esp_debug_backend-1.0.3.dist-info/METADATA
esp_debug_backend-1.0.3.dist-info/WHEEL
esp_debug_backend-1.0.3.dist-info/top_level.txt
esp_debug_backend-1.0.3.dist-info/RECORD
